advanced_report_builder/.DS_Store
advanced_report_builder/__init__.py
advanced_report_builder/admin.py
advanced_report_builder/apps.py
advanced_report_builder/column_types.py
advanced_report_builder/columns.py
advanced_report_builder/customise.py
advanced_report_builder/duplicate.py
advanced_report_builder/exceptions.py
advanced_report_builder/field_types.py
advanced_report_builder/field_utils.py
advanced_report_builder/filter_query.py
advanced_report_builder/form_utils.py
advanced_report_builder/generate_series.py
advanced_report_builder/globals.py
advanced_report_builder/includes.py
advanced_report_builder/models.py
advanced_report_builder/report_builder.py
advanced_report_builder/signals.py
advanced_report_builder/template_types.py
advanced_report_builder/toggle.py
advanced_report_builder/urls.py
advanced_report_builder/utils.py
advanced_report_builder/variable_date.py
advanced_report_builder/view_types.py
advanced_report_builder/widgets.py
advanced_report_builder/.ruff_cache/.gitignore
advanced_report_builder/.ruff_cache/CACHEDIR.TAG
advanced_report_builder/.ruff_cache/0.11.9/16555798982502606642
advanced_report_builder/data_merge/__init__.py
advanced_report_builder/data_merge/utils.py
advanced_report_builder/data_merge/widget.py
advanced_report_builder/migrations/0001_initial.py
advanced_report_builder/migrations/0002_auto_20220209_1657.py
advanced_report_builder/migrations/0003_auto_20220215_1219.py
advanced_report_builder/migrations/0004_customreport.py
advanced_report_builder/migrations/0005_auto_20220303_0958.py
advanced_report_builder/migrations/0006_auto_20220310_1147.py
advanced_report_builder/migrations/0007_auto_20220322_1939.py
advanced_report_builder/migrations/0008_auto_20220404_1144.py
advanced_report_builder/migrations/0009_auto_20230428_1554.py
advanced_report_builder/migrations/0010_auto_20230428_2033.py
advanced_report_builder/migrations/0011_auto_20230620_1449.py
advanced_report_builder/migrations/0012_auto_20230718_1642.py
django_advanced_report_builder-1.2.9.dist-info/licenses/LICENSE
django_advanced_report_builder-1.2.9.dist-info/METADATA
django_advanced_report_builder-1.2.9.dist-info/WHEEL
django_advanced_report_builder-1.2.9.dist-info/top_level.txt
django_advanced_report_builder-1.2.9.dist-info/RECORD
