Metadata-Version: 2.4
Name: django-advanced-report-builder
Version: 1.2.9
Summary: Django app that allows you to build reports from modals
Author: Thomas Turner
License: MIT
Project-URL: Homepage, https://github.com/django-advance-utils/django-advanced-report-builder
Requires-Python: >=3.6
License-File: LICENSE
Requires-Dist: Django>=3.2
Requires-Dist: django-filtered-datatables>=0.0.21
Requires-Dist: django-ajax-helpers>=0.0.20
Requires-Dist: django-nested-modals>=0.0.21
Requires-Dist: time-stamped-model>=0.2.3
Requires-Dist: date-offset>=0.0.2
Requires-Dist: expression-builder>=0.0.12
Dynamic: license-file
